sophos_central_api_connector/ioc_hunter.py
sophos_central_api_connector/sophos_central_api_auth.py
sophos_central_api_connector/sophos_central_api_awssecrets.py
sophos_central_api_connector/sophos_central_api_connector_utils.py
sophos_central_api_connector/sophos_central_api_delete_data.py
sophos_central_api_connector/sophos_central_api_get_data.py
sophos_central_api_connector/sophos_central_api_intelix.py
sophos_central_api_connector/sophos_central_api_live_discover.py
sophos_central_api_connector/sophos_central_api_output.py
sophos_central_api_connector/sophos_central_api_polling.py
sophos_central_api_connector/sophos_central_api_tenants.py
sophos_central_api_connector/sophos_central_hec_splunk.py
sophos_central_api_connector/sophos_central_main.py
sophos_central_api_connector/config/intelix_config.ini
sophos_central_api_connector/config/misp_config.ini
sophos_central_api_connector/config/sophos_central_api_config.py
sophos_central_api_connector/config/sophos_config.ini
sophos_central_api_connector/config/splunk_config.ini
sophos_central_api_connector/docs/alerts.md
sophos_central_api_connector/docs/intelix.md
sophos_central_api_connector/docs/intelix_configuration.md
sophos_central_api_connector/docs/inventory.md
sophos_central_api_connector/docs/ioc_hunter.md
sophos_central_api_connector/docs/local_sites.md
sophos_central_api_connector/docs/misp_configuration.md
sophos_central_api_connector/docs/sophos_configuration.md
sophos_central_api_connector/docs/splunk_configuration.md
sophos_central_api_connector/queries/live_discover_queries/ld_ioc_hunter.sql
sophos_central_api_connector/queries/xdr_queries/xdr_ioc_hunter.sql
sophos_central_api_connector-0.1.6.dist-info/LICENSE
sophos_central_api_connector-0.1.6.dist-info/METADATA
sophos_central_api_connector-0.1.6.dist-info/WHEEL
sophos_central_api_connector-0.1.6.dist-info/top_level.txt
sophos_central_api_connector-0.1.6.dist-info/RECORD
