Metadata-Version: 2.1
Name: sophos-central-api-connector
Version: 0.1.6
Summary: Sophos Central API Connector
Home-page: https://github.com/sophos-cybersecurity/sophos-central-api-connector
Author: Mark Lanczak-Faulds
Author-email: mark.lanczak-faulds@sophos.com
License: UNKNOWN
Platform: UNKNOWN
Classifier: Programming Language :: Python :: 3
Classifier: License :: OSI Approved :: GNU General Public License v3 (GPLv3)
Classifier: Operating System :: OS Independent
Requires-Python: >=3.6
License-File: LICENSE
Requires-Dist: boto3 (>=1.17.21)
Requires-Dist: botocore (>=1.20.21)
Requires-Dist: certifi (>=2020.12.5)
Requires-Dist: chardet (>=4.0.0)
Requires-Dist: configparser (>=5.0.2)
Requires-Dist: docutils (>=0.16)
Requires-Dist: intelix (>=0.1.2)
Requires-Dist: jmespath (>=0.10.0)
Requires-Dist: python-dateutil (>=2.8.1)
Requires-Dist: requests (>=2.25.1)
Requires-Dist: s3transfer (>=0.3.4)
Requires-Dist: six (>=1.15.0)
Requires-Dist: urllib3 (>=1.26.3)
